pyvolcans/__init__.py
pyvolcans/_version.py
pyvolcans/pyvolcans.py
pyvolcans/pyvolcans_func.py
pyvolcans/VOLCANS_csv_files/MeadMagill2014_June2018.csv
pyvolcans/VOLCANS_csv_files/PC81_GR2014_data.csv
pyvolcans/VOLCANS_csv_files/VOTW467_8May18_eruption_data.csv
pyvolcans/VOLCANS_csv_files/VOTW467_8May18_event_data.csv
pyvolcans/VOLCANS_csv_files/VOTW467_8May18_volcano_data.csv
pyvolcans/VOLCANS_csv_files/VOLCANS_code_numbers/README_NUMBERING.md
pyvolcans/VOLCANS_csv_files/VOLCANS_code_numbers/VOTW467_8May18_Eruption_list_textdata_portable.xls
pyvolcans/VOLCANS_csv_files/VOLCANS_code_numbers/VOTW467_8May18_Event_list_textdata_portable.xls
pyvolcans/VOLCANS_csv_files/VOLCANS_code_numbers/VOTW467_8May18_Holocene_list_textdata_portable.xls
pyvolcans/VOLCANS_mat_files/base.py
pyvolcans/VOLCANS_mat_files/VOTW_prepared_data/volc_names.csv
pyvolcans/VOLCANS_mat_files/analogy_mats/AGfinal_allvolcs_ALU_QUET.mat
pyvolcans/VOLCANS_mat_files/analogy_mats/AMfinal_allvolcs_QUET.mat
pyvolcans/VOLCANS_mat_files/analogy_mats/AStfinal_allvolcs_SINA.mat
pyvolcans/VOLCANS_mat_files/analogy_mats/ASzfinal_allvolcs_SINA.mat
pyvolcans/VOLCANS_mat_files/analogy_mats/ATfinal_allvolcs.mat
pyvolcans/VOLCANS_mat_files/data_mats/AGmatrices_ALU_QUET.mat
pyvolcans/VOLCANS_mat_files/data_mats/AMmatrices_QUET.mat
pyvolcans/VOLCANS_mat_files/data_mats/AStmatrices_SINA.mat
pyvolcans/VOLCANS_mat_files/data_mats/ASzmatrices_SINA.mat
pyvolcans/VOLCANS_mat_files/data_mats/ATmatrices.mat
pyvolcans/VOLCANS_matlab_scripts/README_VOLCANS.md
pyvolcans/VOLCANS_matlab_scripts/eruption_size_processing.m
pyvolcans/VOLCANS_matlab_scripts/eruption_style_processing.m
pyvolcans/VOLCANS_matlab_scripts/get_final_AG_allcross.m
pyvolcans/VOLCANS_matlab_scripts/get_final_AM_allcross.m
pyvolcans/VOLCANS_matlab_scripts/get_final_ASt_allcross.m
pyvolcans/VOLCANS_matlab_scripts/get_final_ASz_allcross.m
pyvolcans/VOLCANS_matlab_scripts/get_final_AT_allcross.m
pyvolcans/VOLCANS_matlab_scripts/morphology_processing.m
pyvolcans-1.3.2.dist-info/LICENSE
pyvolcans-1.3.2.dist-info/METADATA
pyvolcans-1.3.2.dist-info/WHEEL
pyvolcans-1.3.2.dist-info/entry_points.txt
pyvolcans-1.3.2.dist-info/top_level.txt
pyvolcans-1.3.2.dist-info/RECORD
