Metadata-Version: 2.1
Name: pyvolcans
Version: 1.3.2
Summary: A tool for identifying volcano analogues.
Home-page: https://github.com/BritishGeologicalSurvey/pyvolcans
Author: BGS Volcanology
Author-email: pablo@bgs.ac.uk
License: UNKNOWN
Platform: UNKNOWN
Classifier: Development Status :: 4 - Beta
Classifier: Intended Audience :: Science/Research
Classifier: License :: OSI Approved :: GNU Lesser General Public License v3 or later (LGPLv3+)
Classifier: Natural Language :: English
Classifier: Operating System :: OS Independent
Classifier: Programming Language :: Python :: 3
Requires-Python: >=3.6
License-File: LICENSE
Requires-Dist: numpy
Requires-Dist: pandas
Requires-Dist: pymatreader
Requires-Dist: matplotlib
Requires-Dist: thefuzz
Provides-Extra: dev
Requires-Dist: flake8 ; extra == 'dev'
Requires-Dist: ipdb ; extra == 'dev'
Requires-Dist: ipython ; extra == 'dev'
Requires-Dist: pytest ; extra == 'dev'
Requires-Dist: pytest-cov ; extra == 'dev'
Requires-Dist: versioneer ; extra == 'dev'
